nampyy/10a.py
nampyy/2a.py
nampyy/3a.py
nampyy/4a.py
nampyy/5a.py
nampyy/6a.py
nampyy/7a.py
nampyy/8a.py
nampyy/9a.py
nampyy/__init__.py
nampyy-0.1.0.dist-info/METADATA
nampyy-0.1.0.dist-info/WHEEL
nampyy-0.1.0.dist-info/top_level.txt
nampyy-0.1.0.dist-info/RECORD
